README
setup.py
src/anyconf/__init__.py
src/anyconf.egg-info/PKG-INFO
src/anyconf.egg-info/SOURCES.txt
src/anyconf.egg-info/dependency_links.txt
src/anyconf.egg-info/top_level.txt