Metadata-Version: 1.0
Name: anyconf
Version: 0.1.0
Summary: Load configuration data from many file formats
Home-page: https://github.com/tctimmeh/anyconf
Author: Tim Court
Author-email: tctimmeh@gmail.com
License: UNKNOWN
Platform: UNKNOWN
Classifier: Development Status :: 2 - Pre-Alpha
Classifier: Intended Audience :: Developers
Classifier: License :: Public Domain
Classifier: License :: Freely Distributable
Classifier: Operating System :: OS Independent
Classifier: Programming Language :: Python :: 2
Classifier: Topic :: Software Development :: Libraries :: Python Modules
